spaic/__init__.py
spaic/Backend/Backend.py
spaic/Backend/Builder.py
spaic/Backend/Torch_Backend.py
spaic/Backend/__init__.py
spaic/IO/Dataloader.py
spaic/IO/Dataset.py
spaic/IO/Environment.py
spaic/IO/Initializer.py
spaic/IO/Pipeline.py
spaic/IO/SignalGenerator.py
spaic/IO/__init__.py
spaic/IO/sampler.py
spaic/IO/utils.py
spaic/Learning/Backprop_RSTDP.py
spaic/Learning/Conv_RSTDP.py
spaic/Learning/Conv_STDP.py
spaic/Learning/FiniteDifference.py
spaic/Learning/Learner.py
spaic/Learning/RSTDP.py
spaic/Learning/Rate_Modulation.py
spaic/Learning/STBP_Learner.py
spaic/Learning/STCA_Learner.py
spaic/Learning/STDP_Learner.py
spaic/Learning/SpikeProp_Learner.py
spaic/Learning/SurrogateBP_Learner.py
spaic/Learning/Tempotron_Learner.py
spaic/Learning/__init__.py
spaic/Learning/surrogate.py
spaic/Library/Library.py
spaic/Library/Network_loader.py
spaic/Library/Network_saver.py
spaic/Library/STCA_music_network.py
spaic/Library/__init__.py
spaic/Monitor/Monitor.py
spaic/Monitor/__init__.py
spaic/Network/Assembly.py
spaic/Network/BaseModule.py
spaic/Network/ConnectPolicy.py
spaic/Network/Connections.py
spaic/Network/Construct.py
spaic/Network/DelayQueue.py
spaic/Network/Network.py
spaic/Network/Operator.py
spaic/Network/Synapse.py
spaic/Network/Topology.py
spaic/Network/__init__.py
spaic/Neuron/Actions.py
spaic/Neuron/Decoders.py
spaic/Neuron/Encoders.py
spaic/Neuron/Generators.py
spaic/Neuron/Module.py
spaic/Neuron/Neuron.py
spaic/Neuron/Node.py
spaic/Neuron/Rewards.py
spaic/Neuron/__init__.py
spaic/UI/OnlineSpikePlot.py
spaic/UI/Visualization.py
spaic/UI/__init__.py
spaic/utils/AnimateScatter.py
spaic/utils/__init__.py
spaic/utils/fftweight.py
spaic/utils/filters.py
spaic/utils/gtgram.py
spaic/utils/memory.py
spaic/utils/plot.py
SPAIC-0.6.3.0.0.dist-info/LICENSE
SPAIC-0.6.3.0.0.dist-info/METADATA
SPAIC-0.6.3.0.0.dist-info/WHEEL
SPAIC-0.6.3.0.0.dist-info/top_level.txt
SPAIC-0.6.3.0.0.dist-info/RECORD
