Metadata-Version: 2.1
Name: SPAIC
Version: 0.6.3.0.0
Summary: The spaic platform simulation training platform is a network construction, forward simulation and learning training platform developed for spiking neural networks.
Home-page: https://github.com/ZhejianglabNCRC/SPAIC/
Author: zjlab
Author-email: hongchf@zhejianglab.com
Maintainer: hongchaofei
Maintainer-email: hongchf@zhejianglab.com
License: Apache-2.0 license
Project-URL: Documentation, https://spaic.readthedocs.io/
Project-URL: Source Code, https://github.com/ZhejianglabNCRC/SPAIC
Project-URL: Issue Tracker, https://github.com/ZhejianglabNCRC/SPAIC/issues
Classifier: Programming Language :: Python
Classifier: Programming Language :: Python :: 3
Classifier: Programming Language :: Python :: 3 :: Only
Classifier: Programming Language :: Python :: 3.6
Classifier: Programming Language :: Python :: 3.7
Classifier: Programming Language :: Python :: 3.8
Classifier: Operating System :: OS Independent
Classifier: License :: OSI Approved :: Apache Software License
Requires-Python: >=3.6
License-File: LICENSE
Requires-Dist: torch (>=1.5.0)
Requires-Dist: matplotlib
Requires-Dist: numpy
Requires-Dist: tqdm
Requires-Dist: scipy
Requires-Dist: pyyaml
Requires-Dist: h5py
